{"sections":{"zp-product-header-content":{"type":"product-header-content-zipifypages","settings":{}},"main":{"type":"main-product","blocks":{"a8fd4036-1b59-4632-8120-b5967333476c":{"type":"accordion_item","settings":{"title":"Features","content":""}},"e0281252-612c-408b-8adb-a6cbf3df4e0f":{"type":"accordion_item","settings":{"title":"Description","content":""}},"d50cf481-c5db-44f8-943c-efefbd6546d1":{"type":"accordion_item","settings":{"title":"specifications","content":""}},"afdd1758-003a-4b58-a07e-26eaeca7c642":{"type":"accordion_item","settings":{"title":"shipping & Delivery","content":""}},"2677505e-b98e-4d84-8b0b-cd9620d41325":{"type":"life_time","settings":{"image":"shopify:\/\/shop_images\/Screenshot_2022-09-30_034132.png","svg_html":"<!--?xml version=\"1.0\" encoding=\"UTF-8\"?--><svg id=\"Layer_1\" xmlns=\"http:\/\/www.w3.org\/2000\/svg\" viewbox=\"0 0 102 102\"><defs><style>.cls-1{font-size:6.46px;}.cls-1,.cls-2,.cls-3{fill:#101010;}.cls-1,.cls-3{font-family:FuturaPT-Medium, 'Futura PT';}.cls-3{font-size:6.46px;}.cls-4{fill:none;stroke:#101010;stroke-miterlimit:10;}<\/style><\/defs><circle class=\"cls-2\" cx=\"17.13\" cy=\"53.96\" r=\"1.49\"><\/circle><circle class=\"cls-2\" cx=\"88.51\" cy=\"51.43\" r=\"1.49\"><\/circle><g><text class=\"cls-3\" transform=\"translate(17.08 41.92) rotate(-73.03)\"><tspan x=\"0\" y=\"0\">L<\/tspan><\/text><text class=\"cls-3\" transform=\"translate(18.26 38.35) rotate(-67.49)\"><tspan x=\"0\" y=\"0\">I<\/tspan><\/text><text class=\"cls-3\" transform=\"translate(19.37 35.72) rotate(-61.71)\"><tspan x=\"0\" y=\"0\">F<\/tspan><\/text><text class=\"cls-3\" transform=\"translate(21.36 32.17) rotate(-54.66)\"><tspan x=\"0\" y=\"0\">E<\/tspan><\/text><text class=\"cls-3\" transform=\"translate(23.98 28.62) rotate(-47.75)\"><tspan x=\"0\" y=\"0\">T<\/tspan><\/text><text class=\"cls-3\" transform=\"translate(26.7 25.75) rotate(-42.17)\"><tspan x=\"0\" y=\"0\">I<\/tspan><\/text><text class=\"cls-3\" transform=\"translate(28.78 23.8) rotate(-34.35)\"><tspan x=\"0\" y=\"0\">M<\/tspan><\/text><text class=\"cls-3\" transform=\"translate(34.37 20.2) rotate(-25.16)\"><tspan x=\"0\" y=\"0\">E<\/tspan><\/text><text class=\"cls-3\" transform=\"translate(38.4 18.42) rotate(-19.27)\"><tspan x=\"0\" y=\"0\"> <\/tspan><\/text><text class=\"cls-3\" transform=\"translate(40.94 17.54) rotate(-13.18)\"><tspan x=\"0\" y=\"0\">R<\/tspan><\/text><text class=\"cls-3\" transform=\"translate(45.46 16.57) rotate(-5.74)\"><tspan x=\"0\" y=\"0\">E<\/tspan><\/text><text class=\"cls-3\" transform=\"translate(49.84 16.21) rotate(1.39)\"><tspan x=\"0\" y=\"0\">P<\/tspan><\/text><text class=\"cls-3\" transform=\"translate(54.11 16.4) rotate(7.97)\"><tspan x=\"0\" y=\"0\">L<\/tspan><\/text><text class=\"cls-3\" transform=\"translate(57.84 16.94) rotate(15.59)\"><tspan x=\"0\" y=\"0\">A<\/tspan><\/text><text class=\"cls-3\" transform=\"translate(62.91 18.45) rotate(24.18)\"><tspan x=\"0\" y=\"0\">C<\/tspan><\/text><text class=\"cls-3\" transform=\"translate(67.56 20.65) rotate(32.12)\"><tspan x=\"0\" y=\"0\">E<\/tspan><\/text><text class=\"cls-3\" transform=\"translate(71.27 22.99) rotate(41.25)\"><tspan x=\"0\" y=\"0\">M<\/tspan><\/text><text class=\"cls-3\" transform=\"translate(76.14 27.49) rotate(50.23)\"><tspan x=\"0\" y=\"0\">E<\/tspan><\/text><text class=\"cls-3\" transform=\"translate(78.92 30.87) rotate(58.79)\"><tspan x=\"0\" y=\"0\">N<\/tspan><\/text><text class=\"cls-3\" transform=\"translate(81.87 36.04) rotate(67)\"><tspan x=\"0\" y=\"0\">T<\/tspan><\/text><g><path class=\"cls-2\" d=\"M44.58,47.85c.88,1.59,.73,3.22,.12,4.87,.21,.06,.41,.12,.61,.17,3.38,.95,6.75,1.92,10.08,3.06,1.15,.39,2.28,.85,3.41,1.29,.28,.11,.54,.28,.81,.41,.05,.02,.15,.05,.16,.04,.03-.06,.07-.13,.06-.19-.05-.24-.1-.48-.17-.71-.48-1.78-.97-3.56-1.45-5.34-.02-.07-.04-.13-.07-.24,.14-.03,.27-.08,.4-.1,.62-.1,1.24-.19,1.86-.3,.05,0,.12-.09,.12-.14,0-.12-.02-.25-.05-.37-.65-2.12-1.3-4.24-1.96-6.36-.1-.31-.03-.54,.2-.77,.77-.77,1.53-1.54,2.29-2.32,.06-.06,.09-.17,.1-.26,.03-.44,.05-.89,.07-1.33,0-.2-.07-.26-.27-.21-.45,.11-.91,.24-1.36,.34-1.49,.32-2.98,.65-4.47,.92-1.37,.25-2.75,.45-4.13,.64-.93,.13-1.87,.2-2.81,.3-2.61,.27-5.23,.32-7.85,.28-.16,0-.24,.02-.28,.21-.22,1.12-.46,2.25-.72,3.36-.2,.88-.43,1.76-.67,2.63-.29,1.06-.59,2.11-.9,3.16-.22,.72-.47,1.44-.72,2.15-.26,.75-.53,1.51-.8,2.26-.08,.23-.18,.46-.28,.69-.08,.16-.24,.31-.25,.47,0,.11-.03,.2-.07,.29-.11,.23-.23,.46-.34,.69-.03,.06-.02,.14-.05,.2-.03,.06-.1,.09-.15,.14,.09,.13,.05,.2-.07,.19,0,.07,.02,.12,0,.17-.11,.24-.22,.48-.35,.75,.19,.02,.35,.04,.52,.07,1.45,.23,2.9,.44,4.34,.7,3.14,.57,6.22,1.35,9.27,2.28,3.12,.95,6.19,2.05,9.17,3.41,1.54,.7,3.05,1.46,4.56,2.23,.75,.38,1.12,1.02,1.11,1.88-.02,1.89,0,3.79,0,5.69h-.05c-.11-.46-.21-.92-.32-1.38-.34-1.5-.69-2.99-1.02-4.49-.03-.14-.09-.23-.22-.3-1.25-.64-2.48-1.3-3.74-1.91-1.79-.87-3.63-1.62-5.5-2.3-1.44-.52-2.89-1.03-4.36-1.48-1.36-.42-2.73-.8-4.11-1.15-1.26-.32-2.52-.59-3.79-.87-.89-.19-1.78-.34-2.67-.51-.03,0-.07-.01-.1-.03-.21-.17-.46-.16-.71-.17-.25,0-.49-.02-.74-.08h.76v-.04c-.37,0-.75,.02-1.12,0-.52-.04-1.04-.12-1.55-.19-.46-.06-.92-.11-1.38-.17-.13-.02-.29-.06-.36-.15-.13-.15-.21-.35-.11-.56,.16-.32,.32-.65,.49-.96,.86-1.54,1.57-3.15,2.21-4.79,.56-1.44,1.07-2.9,1.47-4.39,.34-1.23,.65-2.46,.92-3.7,.26-1.18,.45-2.37,.65-3.56,.11-.68,.19-1.36,.28-2.04,.02-.16,.14-.15,.24-.14,.36,.02,.72,.06,1.08,.07,1.37,.03,2.74,.1,4.12,.08,1.3-.02,2.6-.09,3.9-.2,1.22-.1,2.45-.23,3.66-.41,1.5-.22,2.99-.48,4.47-.78,2.16-.43,4.28-1.01,6.38-1.68,.09-.03,.18-.05,.31-.09,0,.4,0,.76,0,1.13,.02,1.03,.05,2.06,.08,3.08,0,.13-.03,.23-.13,.32-.76,.72-1.51,1.45-2.27,2.16-.23,.22-.3,.4-.18,.73,.29,.78,.52,1.59,.77,2.39,.48,1.49,.95,2.98,1.43,4.47,.03,.11,.06,.22,.08,.33,.06,.39-.11,.65-.49,.74-.47,.11-.94,.21-1.41,.31-.24,.05-.27,.11-.21,.35,.26,.97,.52,1.94,.78,2.91,.32,1.19,.64,2.37,.96,3.56,.14,.51-.07,.82-.6,.92-.23,.04-.43,.02-.65-.09-1.89-.96-3.81-1.85-5.77-2.65-2-.82-4.03-1.55-6.1-2.16-1.37-.4-2.75-.76-4.15-1.03-.74-.14-1.48-.24-2.23-.36-.15-.02-.17-.09-.09-.24,.18-.35,.38-.68,.55-1.04,.68-1.41,1.21-2.87,1.46-4.42,.01-.06,.01-.13,.02-.19,0-.06,.02-.12,.03-.17h.05Z\"><\/path><path class=\"cls-2\" d=\"M38.63,37.93l.35-6.94c.41,.22,.8,.43,1.18,.64,1.66,.91,3.32,1.82,4.98,2.73,.15,.08,.25,.09,.4-.01,1.67-1.11,3.34-2.21,5.01-3.3,.07-.04,.18-.06,.26-.03,1.77,.5,3.54,1,5.3,1.51,.14,.04,.22,.02,.33-.08,2.04-1.94,4.09-3.87,6.14-5.8,.06-.05,.11-.1,.19-.17,0,.06,.01,.1,.01,.14-.01,2.48-.03,4.97-.03,7.45,0,.14-.05,.2-.17,.26-1.63,.75-3.31,1.34-5.02,1.84-1.69,.5-3.4,.92-5.13,1.21-.98,.17-1.97,.33-2.95,.45-.81,.1-1.63,.18-2.44,.22-1.27,.07-2.55,.13-3.83,.13-1.11,0-2.23-.08-3.34-.13-.4-.02-.79-.07-1.22-.12Z\"><\/path><\/g><circle class=\"cls-4\" cx=\"51\" cy=\"51\" r=\"45.61\"><\/circle><text class=\"cls-1\" transform=\"translate(83.92 60.12) rotate(107.58)\"><tspan x=\"0\" y=\"0\">L<\/tspan><\/text><text class=\"cls-1\" transform=\"translate(82.71 63.67) rotate(113.12)\"><tspan x=\"0\" y=\"0\">I<\/tspan><\/text><text class=\"cls-1\" transform=\"translate(81.56 66.29) rotate(118.9)\"><tspan x=\"0\" y=\"0\">F<\/tspan><\/text><text class=\"cls-1\" transform=\"translate(79.54 69.83) rotate(125.95)\"><tspan x=\"0\" y=\"0\">E<\/tspan><\/text><text class=\"cls-1\" transform=\"translate(76.88 73.35) rotate(132.86)\"><tspan x=\"0\" y=\"0\">T<\/tspan><\/text><text class=\"cls-1\" transform=\"translate(74.12 76.19) rotate(138.44)\"><tspan x=\"0\" y=\"0\">I<\/tspan><\/text><text class=\"cls-1\" transform=\"translate(72.01 78.14) rotate(146.3)\"><tspan x=\"0\" y=\"0\">M<\/tspan><\/text><text class=\"cls-1\" transform=\"translate(66.4 81.66) rotate(155.45)\"><tspan x=\"0\" y=\"0\">E<\/tspan><\/text><text class=\"cls-1\" transform=\"translate(62.36 83.39) rotate(161.34)\"><tspan x=\"0\" y=\"0\"> <\/tspan><\/text><text class=\"cls-1\" transform=\"translate(59.8 84.24) rotate(167.43)\"><tspan x=\"0\" y=\"0\">R<\/tspan><\/text><text class=\"cls-1\" transform=\"translate(55.28 85.16) rotate(174.87)\"><tspan x=\"0\" y=\"0\">E<\/tspan><\/text><text class=\"cls-1\" transform=\"translate(50.89 85.48) rotate(-178)\"><tspan x=\"0\" y=\"0\">P<\/tspan><\/text><text class=\"cls-1\" transform=\"translate(46.62 85.25) rotate(-171.42)\"><tspan x=\"0\" y=\"0\">L<\/tspan><\/text><text class=\"cls-1\" transform=\"translate(42.89 84.66) rotate(-163.8)\"><tspan x=\"0\" y=\"0\">A<\/tspan><\/text><text class=\"cls-1\" transform=\"translate(37.84 83.1) rotate(-155.21)\"><tspan x=\"0\" y=\"0\">C<\/tspan><\/text><text class=\"cls-1\" transform=\"translate(33.21 80.85) rotate(-147.27)\"><tspan x=\"0\" y=\"0\">E<\/tspan><\/text><text class=\"cls-1\" transform=\"translate(29.53 78.48) rotate(-138.14)\"><tspan x=\"0\" y=\"0\">M<\/tspan><\/text><text class=\"cls-1\" transform=\"translate(24.71 73.92) rotate(-129.16)\"><tspan x=\"0\" y=\"0\">E<\/tspan><\/text><text class=\"cls-1\" transform=\"translate(21.97 70.51) rotate(-120.6)\"><tspan x=\"0\" y=\"0\">N<\/tspan><\/text><text class=\"cls-1\" transform=\"translate(19.07 65.31) rotate(-112.39)\"><tspan x=\"0\" y=\"0\">T<\/tspan><\/text><\/g><\/svg>","content":"Our LIFETIME REPLACEMENTS program is designed to add the most value to our customers.","modal_subtitle":"LIFETIME REPLACEMENT","modal_title":"How it works","step_title_1":"Step 1","step_content_1":"<a href=\"https:\/\/for-a-kings-loot.myshopify.com\/account\/register\">Please <b>create an account<\/b><\/a>. (Make sure your shipping and contact information is correct).","step_title_2":"Step 2","step_content_2":"Please fill out this <a href=\"https:\/\/docs.google.com\/forms\/d\/e\/1FAIpQLSd35k5WipSVkje0HZe1m9R731sAWr1UHlznj5jabUg4B9RR\"><b>Google Form<\/b><\/a>.","step_title_3":"Step 3","step_content_3":"Once your replacement is approved, we will email you an invoice with instructions on how to pay and send the product back. This takes 2-3 weeks."}},"0b22858f-996b-4de6-9b01-42babbcde14c":{"type":"slider_image","settings":{"image":"{{ product.metafields.custom.see_it_action_image_1_mobile.value }}"}},"c3ec9639-7865-4767-95c6-0899c4925537":{"type":"slider_image","settings":{"image":"{{ product.metafields.custom.see_it_action_image_2_mobile.value }}"}},"57b89f42-e4f6-4744-90c9-8c859a926517":{"type":"slider_image","settings":{"image":"{{ product.metafields.custom.see_it_action_image_3_mobile.value }}"}},"9f7bf3e1-d822-4fa8-95e2-dcafc49730f7":{"type":"slider_image","settings":{"image":"{{ product.metafields.custom.see_it_action_image_1_mobile.value }}"}},"ce358240-4972-4d41-97f9-b282e420d2cd":{"type":"slider_video","settings":{"video_url":"https:\/\/www.youtube.com\/embed\/1m5G4rg9Ytw"}},"d25e668b-b5b3-479a-b26c-d32f96fdc922":{"type":"product","settings":{"product":"bi-fold","feature_page":"bifold-features","specification_page":"bifold-specifications"}},"9fdbe085-95e9-4d12-b210-f2fbef292dbf":{"type":"product","settings":{"product":"traditional-wallet-8-10-cards-rfid","feature_page":"her-traditional-features","specification_page":"her-traditional-specifications"}},"b3e30a59-92e3-4c1d-8a7b-8ab6f5263273":{"type":"product","settings":{"product":"journey-6-8-cards-womens","feature_page":"her-journey-features","specification_page":"her-journey-specifications"}},"6b3f880e-58dc-4a4a-829f-3ab6405ec627":{"type":"product","settings":{"product":"hybrid","feature_page":"traditional-features","specification_page":"traditional-specifications"}},"9377ba0b-8bec-413a-80a5-63b16546ccca":{"type":"product","settings":{"product":"journey","feature_page":"journey-features","specification_page":"journey-specifications"}},"24280fd7-3d91-421c-9411-d9abf380ed68":{"type":"product","settings":{"product":"kings-back","feature_page":"kings-back-features","specification_page":"kings-back-wallet-specifications"}},"770a00e9-3e55-4ff6-a02c-9d06d5747613":{"type":"product","settings":{"product":"kings-back-wallet-magsafe-case-magnet-sticker","feature_page":"kings-back-magsafe-case-magnet-sticker-features","specification_page":"kings-back-magsafe-case-magnet-sticker-specifications"}},"2e5cc886-26f1-4b0a-a20e-5ae9d00571f7":{"type":"product","settings":{"product":"kings-loot-cash-clip","feature_page":"kings-clip-features","specification_page":"kings-clip-specifications"}},"a3ffb897-dc60-4770-842c-3d52e5ff4fcf":{"type":"product","settings":{"product":"kings-conditioner","feature_page":"kings-conditioner-features","specification_page":"kings-conditioner-specifications"}},"40e94a0f-6d22-48e5-ab2b-f70b543775ec":{"type":"product","settings":{"product":"kings-keychain","feature_page":"kings-keychain-features","specification_page":"kings-keychain-specifications"}},"33df1571-80b4-4c01-be9e-ea9c6fac4e99":{"type":"product","settings":{"product":"leather-cord-belt","feature_page":"leather-cord-belt-features","specification_page":"leather-cord-belt-specifications"}},"939df0c7-505f-45cd-ae6c-4a6f24305bc9":{"type":"product","settings":{"product":"leather-magsafe-iphone-cases","feature_page":"leather-magsafe-iphone-case-features","specification_page":"leather-magsafe-iphone-cases-specifications"}},"ff7b5860-4ba6-43a9-83c4-6dabbdc6d01e":{"type":"product","settings":{"product":"leather-sleeve-airtag","feature_page":"leather-sleeve-for-airtag-features","specification_page":"leather-sleeve-for-airtag-specifications"}},"3374ac08-8d3e-437f-a3e0-a081612d629d":{"type":"product","settings":{"product":"magsafe-case-magnet-sticker","feature_page":"magsafe-case-magnet-sticker-features","specification_page":"magsafe-case-magnet-sticker-specifications"}},"319e3985-7561-4d03-be3f-8fdf37b515d8":{"type":"product","settings":{"product":"mini-2-0","feature_page":"copy-of-traveler-features","specification_page":"mini-2-0-wallet-specifications"}},"3873180f-3900-44a3-a3ef-80f626ae0683":{"type":"product","settings":{"product":"mini-3-0","feature_page":"mini-3-0-features","specification_page":"mini-3-0-wallet-specifications"}},"44c8085a-9d25-4aaf-bd67-cf999cb7a79f":{"type":"product","settings":{"product":"mini-wristlet","feature_page":"mini-wristlet-features","specification_page":"mini-wristlet-specifications"}},"42a5918a-2378-4837-b328-5d3f7d667066":{"type":"product","settings":{"product":"matte-wallet-limited-edition","feature_page":"traditional-features","specification_page":"traditional-specifications"}},"043c8474-1479-44e3-8909-410897fb732d":{"type":"product","settings":{"product":"traveler-wallet","feature_page":"traveler-features","specification_page":"traveler-wallet-specifications"}},"64ec3c26-3614-4dd0-ae95-cf64cccd1d1e":{"type":"product","settings":{"product":"classic-watch-strap","feature_page":"classic-watch-strap-features","specification_page":"classic-watch-strap-specifications"}},"a9dfdcac-6e0c-48f4-bb3c-bf2fff46ee1e":{"type":"product","settings":{"product":"king-fold","feature_page":"kings-fold-features","specification_page":"kings-fold-specifications"}},"a03ce783-a676-43fb-8c6b-9c65b5af20df":{"type":"product","settings":{"product":"quick-release-keychain","feature_page":"quick-release-keychain-features","specification_page":"quick-release-keychain-specifications"}},"674cd996-5f16-45ca-8b6f-4af3ecc3e455":{"type":"product","settings":{"product":"camo-collection","feature_page":"camo-collection-features","specification_page":"camo-collection-specifications"}},"16007ee3-d538-4052-bda4-2420472d7201":{"type":"product","settings":{"product":"everyday-access","feature_page":"traditional-features","specification_page":"traditional-specifications"}},"c5d1e6ae-c034-4495-aabd-6d0ac6b78bdd":{"type":"product","settings":{"product":"everyday-carry-bundle","feature_page":"traditional-features","specification_page":"traditional-specifications"}},"a79cc2a1-c345-4922-ad70-8ffc4cec77eb":{"type":"product","settings":{"product":"the-luxe","feature_page":"the-luxe-features","specification_page":"the-luxe-specifications"}},"32211370-292a-4b6e-988c-c2c426cb8adf":{"type":"product","settings":{"product":"her-kings-back-wallet","feature_page":"kings-back-features","specification_page":"kings-back-wallet-specifications"}},"973c7f76-70b2-40e2-956a-32866dc2b632":{"type":"product","settings":{"product":"her-mini-2-0","feature_page":"copy-of-traveler-features","specification_page":"mini-2-0-wallet-specifications"}},"439b7c70-8c92-435f-bcb2-252274f4d1ba":{"type":"product","settings":{"product":"her-mini-3-0-wallet","feature_page":"mini-3-0-features","specification_page":"mini-3-0-wallet-specifications"}},"8f7f1306-8209-40f3-8e32-34254484d0f5":{"type":"product","settings":{"product":"her-leather-sleeve-for-airtag","feature_page":"leather-sleeve-for-airtag-features","specification_page":"leather-sleeve-for-airtag-specifications"}}},"block_order":["a8fd4036-1b59-4632-8120-b5967333476c","e0281252-612c-408b-8adb-a6cbf3df4e0f","d50cf481-c5db-44f8-943c-efefbd6546d1","afdd1758-003a-4b58-a07e-26eaeca7c642","2677505e-b98e-4d84-8b0b-cd9620d41325","0b22858f-996b-4de6-9b01-42babbcde14c","c3ec9639-7865-4767-95c6-0899c4925537","57b89f42-e4f6-4744-90c9-8c859a926517","9f7bf3e1-d822-4fa8-95e2-dcafc49730f7","ce358240-4972-4d41-97f9-b282e420d2cd","d25e668b-b5b3-479a-b26c-d32f96fdc922","9fdbe085-95e9-4d12-b210-f2fbef292dbf","b3e30a59-92e3-4c1d-8a7b-8ab6f5263273","6b3f880e-58dc-4a4a-829f-3ab6405ec627","9377ba0b-8bec-413a-80a5-63b16546ccca","24280fd7-3d91-421c-9411-d9abf380ed68","770a00e9-3e55-4ff6-a02c-9d06d5747613","2e5cc886-26f1-4b0a-a20e-5ae9d00571f7","a3ffb897-dc60-4770-842c-3d52e5ff4fcf","40e94a0f-6d22-48e5-ab2b-f70b543775ec","33df1571-80b4-4c01-be9e-ea9c6fac4e99","939df0c7-505f-45cd-ae6c-4a6f24305bc9","ff7b5860-4ba6-43a9-83c4-6dabbdc6d01e","3374ac08-8d3e-437f-a3e0-a081612d629d","319e3985-7561-4d03-be3f-8fdf37b515d8","3873180f-3900-44a3-a3ef-80f626ae0683","44c8085a-9d25-4aaf-bd67-cf999cb7a79f","42a5918a-2378-4837-b328-5d3f7d667066","043c8474-1479-44e3-8909-410897fb732d","64ec3c26-3614-4dd0-ae95-cf64cccd1d1e","a9dfdcac-6e0c-48f4-bb3c-bf2fff46ee1e","a03ce783-a676-43fb-8c6b-9c65b5af20df","674cd996-5f16-45ca-8b6f-4af3ecc3e455","16007ee3-d538-4052-bda4-2420472d7201","c5d1e6ae-c034-4495-aabd-6d0ac6b78bdd","a79cc2a1-c345-4922-ad70-8ffc4cec77eb","32211370-292a-4b6e-988c-c2c426cb8adf","973c7f76-70b2-40e2-956a-32866dc2b632","439b7c70-8c92-435f-bcb2-252274f4d1ba","8f7f1306-8209-40f3-8e32-34254484d0f5"],"settings":{"spacing_desktop":10,"spacing_mobile":10,"show_dynamic_checkout":false,"show_shipping":true,"ship_text":"{{ product.metafields.custom.shipping_text.value }}","ship_modal_text":"5 Business days after the cutoff (2 PM MST)","shipping_info":"shipping-delivery","show_info":true,"content":""}},"1660254489fa6e6293":{"type":"section_icon-block","disabled":true,"blocks":{"48de195b-6fbd-4b86-b28e-52fa78e6a960":{"type":"item","settings":{"svg_icon":"","lazy_loading":"lazy","image":"{{ product.metafields.custom.icon_block_image_1.value }}","mobile_image":"{{ product.metafields.custom.icon_block_image_1.value }}","image_x_position":50,"image_y_position":50,"title":"{{ product.metafields.custom.icon_block_title_1.value }}"}},"0c62024c-ee50-474b-8655-9946ccb33553":{"type":"item","settings":{"svg_icon":"","lazy_loading":"lazy","image":"{{ product.metafields.custom.icon_block_image_2.value }}","mobile_image":"{{ product.metafields.custom.icon_block_image_2.value }}","image_x_position":50,"image_y_position":50,"title":"{{ product.metafields.custom.icon_block_title_2.value }}"}},"993ee4d1-40a9-44c0-872f-648a8942f368":{"type":"item","settings":{"svg_icon":"","lazy_loading":"lazy","image":"{{ product.metafields.custom.icon_block_image_3.value }}","mobile_image":"{{ product.metafields.custom.icon_block_image_3.value }}","image_x_position":50,"image_y_position":50,"title":"{{ product.metafields.custom.icon_block_title_3.value }}"}},"5556d73e-2cc9-41be-b9af-4d51ee236468":{"type":"item","settings":{"svg_icon":"","lazy_loading":"lazy","image":"{{ product.metafields.custom.icon_block_image_4.value }}","mobile_image":"{{ product.metafields.custom.icon_block_image_4.value }}","image_x_position":50,"image_y_position":50,"title":"{{ product.metafields.custom.icon_block_title_4.value }}"}}},"block_order":["48de195b-6fbd-4b86-b28e-52fa78e6a960","0c62024c-ee50-474b-8655-9946ccb33553","993ee4d1-40a9-44c0-872f-648a8942f368","5556d73e-2cc9-41be-b9af-4d51ee236468"],"settings":{"spacing_desktop":"56","spacing_mobile":"32","width":"full","title":"","content":""}},"1660254513edad9898":{"type":"section_image-slider","blocks":{"78c3bf41-9e58-43d4-bf77-eadec4ebc1a7":{"type":"image","settings":{"lazy_loading":"lazy","image":"{{ product.metafields.custom.see_it_action_image_1_desktop.value }}","image_x_position":50,"image_y_position":50}},"ec50b42d-2f7f-4fef-a07f-b96d7654e14f":{"type":"image","settings":{"lazy_loading":"lazy","image":"{{ product.metafields.custom.see_it_action_image_2_desktop.value }}","image_x_position":50,"image_y_position":50}},"3e2cbb10-4405-44f8-b0e2-740deab26ded":{"type":"image","settings":{"lazy_loading":"lazy","image":"{{ product.metafields.custom.see_it_action_image_3_desktop.value }}","image_x_position":50,"image_y_position":50}},"d1d8f916-2686-4bfa-bf11-4c47dd7e06d2":{"type":"video","settings":{"video_url":"https:\/\/www.youtube.com\/embed\/1m5G4rg9Ytw"}}},"block_order":["78c3bf41-9e58-43d4-bf77-eadec4ebc1a7","ec50b42d-2f7f-4fef-a07f-b96d7654e14f","3e2cbb10-4405-44f8-b0e2-740deab26ded","d1d8f916-2686-4bfa-bf11-4c47dd7e06d2"],"settings":{"title":"See it in action","width":"contained","background_colour":"rgba(0,0,0,0)","spacing_desktop":"56","spacing_mobile":"32","auto_play":false,"show_arrows":true,"show_pagination":false}},"1658771655200fb38f":{"type":"section_product-additional","blocks":{"77eb9903-17a0-4211-ae51-79be8bb73a69":{"type":"item","settings":{"image_position":"left","background":"","lazy_loading":"lazy","image":"{{ product.metafields.custom.product_additional_image_1.value }}","image_x_position":50,"image_y_position":50,"title":"{{ product.metafields.custom.product_additional_title_1.value }}","content":"<p>{{ product.metafields.custom.product_additional_content_1 | metafield_tag }}<\/p>"}},"34ba1623-e514-4246-8c40-098aee626b56":{"type":"item","settings":{"image_position":"right","background":"","lazy_loading":"lazy","image":"{{ product.metafields.custom.product_additional_image_2.value }}","image_x_position":50,"image_y_position":50,"title":"{{ product.metafields.custom.product_additional_title_2.value }}","content":"<p>{{ product.metafields.custom.product_additional_content_2 | metafield_tag }}<\/p>"}},"cbe23ef1-f9c9-4e10-80f8-54a046b251ee":{"type":"item","settings":{"image_position":"left","background":"","lazy_loading":"lazy","image":"{{ product.metafields.custom.product_additional_image_3.value }}","image_x_position":50,"image_y_position":50,"title":"{{ product.metafields.custom.product_additional_title_3.value }}","content":"<p>{{ product.metafields.custom.product_additional_content_3 | metafield_tag }}<\/p>"}},"eafddaeb-8195-47e1-b8e8-9c5fa5a45178":{"type":"item","settings":{"image_position":"right","background":"","lazy_loading":"lazy","image":"{{ product.metafields.custom.product_additional_image_4.value }}","image_x_position":50,"image_y_position":50,"title":"{{ product.metafields.custom.product_additional_title_4.value }}","content":"<p>{{ product.metafields.custom.product_additional_content_4 | metafield_tag }}<\/p>"}}},"block_order":["77eb9903-17a0-4211-ae51-79be8bb73a69","34ba1623-e514-4246-8c40-098aee626b56","cbe23ef1-f9c9-4e10-80f8-54a046b251ee","eafddaeb-8195-47e1-b8e8-9c5fa5a45178"],"settings":{"spacing_desktop":"56","spacing_mobile":"32","width":"contained","custom_class":""}},"3440e4d4-2cf2-4957-9013-6e4a8feee0a2":{"type":"section_image-gallery","blocks":{"15698ae5-4bd0-4af1-bb9d-23206f8f5caf":{"type":"image","settings":{"lazy_loading":"lazy","image":"{{ product.metafields.custom.gallery_image_1.value }}","image_x_position":50,"image_y_position":50}},"ae923272-4341-4b55-81ff-14a0b341b8ba":{"type":"image","settings":{"lazy_loading":"lazy","image":"{{ product.metafields.custom.gallery_image_2.value }}","image_x_position":50,"image_y_position":50}}},"block_order":["15698ae5-4bd0-4af1-bb9d-23206f8f5caf","ae923272-4341-4b55-81ff-14a0b341b8ba"],"settings":{"title":"","width":"full","background_colour":"rgba(0,0,0,0)","spacing_desktop":"56","spacing_mobile":"32"}},"16603169835bac4685":{"type":"apps","blocks":{"4af241be-d0f1-41d3-90fb-532efa587e10":{"type":"shopify:\/\/apps\/stamped-product-reviews-ugc\/blocks\/star-rating-badge\/a103faaf-2125-4b0e-89fa-de5149736723","disabled":true,"settings":{"use_metafields":true,"sku_tagtype":"sku","is_featured_product":false,"featured_product_handle":""}},"fb821856-be87-4c75-8ca1-2066f73567a5":{"type":"shopify:\/\/apps\/product-reviews\/blocks\/reviews\/bae150af-8da8-48b2-9867-398188115e5f","disabled":true,"settings":{}},"da082125-962e-4fdf-b730-522436ae3f4f":{"type":"shopify:\/\/apps\/product-reviews\/blocks\/star_rating\/bae150af-8da8-48b2-9867-398188115e5f","disabled":true,"settings":{"stars_fill_color":"#e2b41c","star_size":15,"text_align":"center","product":"{{product}}","stars_text_empty":"No reviews"}},"7b56a6bb-7d79-499f-8ff6-0f6c297bfa78":{"type":"shopify:\/\/apps\/stamped-product-reviews-ugc\/blocks\/main-widget\/a103faaf-2125-4b0e-89fa-de5149736723","settings":{"animation":true,"tags_exclude":"","tags_include":"","search":"","linkify":true,"use_metafields":true,"sku_tagtype":"sku"}}},"block_order":["4af241be-d0f1-41d3-90fb-532efa587e10","fb821856-be87-4c75-8ca1-2066f73567a5","da082125-962e-4fdf-b730-522436ae3f4f","7b56a6bb-7d79-499f-8ff6-0f6c297bfa78"],"settings":{"include_margins":true}},"1658778067685eb81a":{"type":"section_recommended-products","disabled":true,"settings":{"spacing_desktop":"56","spacing_mobile":"32","width":"contained","title":"You may also like","button_label":"","button_target":false,"button_link":"","button_type":"primary","product_list":["camo-collection","bi-fold","classic-watch-strap","kings-sleeve-clip-combo"]}},"1658778343143fa2f1":{"type":"section_featured-products","disabled":true,"settings":{"spacing_desktop":"56","spacing_mobile":"32","width":"contained","max_count":4,"button_label":"","button_target":false,"button_link":"","button_type":"primary"}},"zp-product-footer-content":{"type":"product-footer-content-zipifypages","settings":{}}},"order":["zp-product-header-content","main","1660254489fa6e6293","1660254513edad9898","1658771655200fb38f","3440e4d4-2cf2-4957-9013-6e4a8feee0a2","16603169835bac4685","1658778067685eb81a","1658778343143fa2f1","zp-product-footer-content"]}